aspose/imaging/py.typed
aspose/pycore/py.typed
aspose/pycore/__init__.pyi
aspose/pyreflection/py.typed
aspose/pyreflection/__init__.pyi
aspose/pydrawing/py.typed
aspose/pydrawing/__init__.pyi
aspose/pydrawing/design.pyi
aspose/pydrawing/drawing2d.pyi
aspose/pydrawing/imaging.pyi
aspose/pydrawing/printing.pyi
aspose/pydrawing/text.pyi
aspose/imaging/__init__.pyi
aspose/imaging/apsbuilder/__init__.pyi
aspose/imaging/apsbuilder/dib/__init__.pyi
aspose/imaging/asynctask/__init__.pyi
aspose/imaging/brushes/__init__.pyi
aspose/imaging/dithering/__init__.pyi
aspose/imaging/exif/__init__.pyi
aspose/imaging/exif/enums/__init__.pyi
aspose/imaging/extensions/__init__.pyi
aspose/imaging/fileformats/__init__.pyi
aspose/imaging/fileformats/apng/__init__.pyi
aspose/imaging/fileformats/avif/__init__.pyi
aspose/imaging/fileformats/bigtiff/__init__.pyi
aspose/imaging/fileformats/bmp/__init__.pyi
aspose/imaging/fileformats/bmp/structures/__init__.pyi
aspose/imaging/fileformats/cdr/__init__.pyi
aspose/imaging/fileformats/cdr/const/__init__.pyi
aspose/imaging/fileformats/cdr/enum/__init__.pyi
aspose/imaging/fileformats/cdr/objects/__init__.pyi
aspose/imaging/fileformats/cdr/types/__init__.pyi
aspose/imaging/fileformats/cmx/__init__.pyi
aspose/imaging/fileformats/cmx/objectmodel/__init__.pyi
aspose/imaging/fileformats/cmx/objectmodel/enums/__init__.pyi
aspose/imaging/fileformats/cmx/objectmodel/specs/__init__.pyi
aspose/imaging/fileformats/cmx/objectmodel/styles/__init__.pyi
aspose/imaging/fileformats/core/__init__.pyi
aspose/imaging/fileformats/core/vectorpaths/__init__.pyi
aspose/imaging/fileformats/dicom/__init__.pyi
aspose/imaging/fileformats/djvu/__init__.pyi
aspose/imaging/fileformats/dng/__init__.pyi
aspose/imaging/fileformats/dng/decoder/__init__.pyi
aspose/imaging/fileformats/emf/__init__.pyi
aspose/imaging/fileformats/emf/dtyp/__init__.pyi
aspose/imaging/fileformats/emf/dtyp/commondatastructures/__init__.pyi
aspose/imaging/fileformats/emf/emf/__init__.pyi
aspose_imaging_python_net-25.12.0.dist-info/METADATA
aspose_imaging_python_net-25.12.0.dist-info/WHEEL
aspose_imaging_python_net-25.12.0.dist-info/entry_points.txt
aspose_imaging_python_net-25.12.0.dist-info/top_level.txt
aspose_imaging_python_net-25.12.0.dist-info/RECORD