Metadata-Version: 2.1
Name: aspose-imaging-python-net
Version: 25.12.0
Summary: Aspose.Imaging for Python via .NET is Another Python Imaging Library. It allows developers to easily create, load, manipulate, convert, compress images or photos using this API.
Home-page: https://products.aspose.com/imaging/python-net
Author: Aspose
License: Free To Use But Restricted,Other/Proprietary License
Project-URL: API Reference, https://reference.aspose.com/imaging/python-net/
Project-URL: Blog, https://blog.aspose.com/categories/aspose.imaging-product-family/
Project-URL: Demos, https://products.aspose.app/imaging/family
Project-URL: Docs, https://docs.aspose.com/imaging/python-net/
Project-URL: Examples, https://github.com/aspose-imaging/Aspose.Imaging-for-Python-NET
Project-URL: Free Support, https://forum.aspose.com/c/imaging
Project-URL: Release Notes, https://releases.aspose.com/imaging/python-net/release-notes/2025/aspose-imaging-for-python-net-25-12-release-notes/
Project-URL: Temporary License, https://purchase.aspose.com/temporary-license
Keywords: image,convert,manipulate,drawing,load,update,save,merge,crop,resize,flip,rotate,canvas,graphics,jpeg,png,gif,svg,tiff,bigtiff,bmp,dicom,eps,tga,webp,cdr,cmx,djvu,dng,tga,html5,dxf,raster,metafiles,wmf,emf,fodg,ico,pdf,svgz,emz,wmz
Platform: linux_x86_64
Classifier: Development Status :: 5 - Production/Stable
Classifier: Intended Audience :: Developers
Classifier: Intended Audience :: Education
Classifier: Intended Audience :: Other Audience
Classifier: Operating System :: Microsoft :: Windows
Classifier: Operating System :: POSIX :: Linux
Classifier: Operating System :: Unix
Classifier: Operating System :: MacOS :: MacOS X
Classifier: Topic :: Office/Business
Classifier: Topic :: Software Development
Classifier: Topic :: Software Development :: Libraries
Classifier: Topic :: Multimedia :: Graphics
Classifier: Topic :: Multimedia :: Graphics :: Graphics Conversion
Classifier: Topic :: Scientific/Engineering :: Image Processing
Classifier: Programming Language :: Python :: 3
Classifier: Programming Language :: Python :: 3 :: Only
Classifier: Programming Language :: Python :: 3.5
Classifier: Programming Language :: Python :: 3.6
Classifier: Programming Language :: Python :: 3.7
Classifier: Programming Language :: Python :: 3.8
Classifier: Programming Language :: Python :: 3.9
Classifier: Programming Language :: Python :: 3.10
Classifier: Programming Language :: Python :: 3.11
Classifier: Programming Language :: Python :: 3.12
Classifier: Programming Language :: Python :: 3.13
Requires-Python: >=3.5,<3.14
